spimdisasm/__init__.py
spimdisasm/__main__.py
spimdisasm/py.typed
spimdisasm/common/CompilerConfig.py
spimdisasm/common/Context.py
spimdisasm/common/ContextSymbols.py
spimdisasm/common/ElementBase.py
spimdisasm/common/FileSectionType.py
spimdisasm/common/FileSplitFormat.py
spimdisasm/common/GlobalConfig.py
spimdisasm/common/GpAccesses.py
spimdisasm/common/OrderedEnum.py
spimdisasm/common/Relocation.py
spimdisasm/common/SortedDict.py
spimdisasm/common/SymbolsSegment.py
spimdisasm/common/Utils.py
spimdisasm/common/__init__.py
spimdisasm/disasmdis/DisasmdisInternals.py
spimdisasm/disasmdis/__init__.py
spimdisasm/disasmdis/__main__.py
spimdisasm/elf32/Elf32Constants.py
spimdisasm/elf32/Elf32Dyns.py
spimdisasm/elf32/Elf32File.py
spimdisasm/elf32/Elf32GlobalOffsetTable.py
spimdisasm/elf32/Elf32Header.py
spimdisasm/elf32/Elf32RegInfo.py
spimdisasm/elf32/Elf32Rels.py
spimdisasm/elf32/Elf32SectionHeaders.py
spimdisasm/elf32/Elf32StringTable.py
spimdisasm/elf32/Elf32Syms.py
spimdisasm/elf32/__init__.py
spimdisasm/elfObjDisasm/ElfObjDisasmInternals.py
spimdisasm/elfObjDisasm/__init__.py
spimdisasm/elfObjDisasm/__main__.py
spimdisasm/frontendCommon/FrontendUtilities.py
spimdisasm/frontendCommon/__init__.py
spimdisasm/mips/FilesHandlers.py
spimdisasm/mips/FuncRodataEntry.py
spimdisasm/mips/InstructionConfig.py
spimdisasm/mips/MipsFileBase.py
spimdisasm/mips/MipsFileSplits.py
spimdisasm/mips/__init__.py
spimdisasm/mips/sections/MipsSectionBase.py
spimdisasm/mips/sections/MipsSectionBss.py
spimdisasm/mips/sections/MipsSectionData.py
spimdisasm/mips/sections/MipsSectionGccExceptTable.py
spimdisasm/mips/sections/MipsSectionRelocZ64.py
spimdisasm/mips/sections/MipsSectionRodata.py
spimdisasm/mips/sections/MipsSectionText.py
spimdisasm/mips/sections/__init__.py
spimdisasm/mips/symbols/MipsSymbolBase.py
spimdisasm/mips/symbols/MipsSymbolBss.py
spimdisasm/mips/symbols/MipsSymbolData.py
spimdisasm/mips/symbols/MipsSymbolFunction.py
spimdisasm/mips/symbols/MipsSymbolGccExceptTable.py
spimdisasm-1.39.3.dist-info/licenses/LICENSE
spimdisasm-1.39.3.dist-info/METADATA
spimdisasm-1.39.3.dist-info/WHEEL
spimdisasm-1.39.3.dist-info/entry_points.txt
spimdisasm-1.39.3.dist-info/top_level.txt
spimdisasm-1.39.3.dist-info/RECORD
