Metadata-Version: 2.4
Name: spimdisasm
Version: 1.39.3
Summary: MIPS disassembler
Author-email: Anghelo Carvajal <angheloalf95@gmail.com>
License: MIT License
Project-URL: Repository, https://github.com/Decompollaborate/spimdisasm
Project-URL: Issues, https://github.com/Decompollaborate/spimdisasm/issues
Project-URL: Changelog, https://github.com/Decompollaborate/spimdisasm/blob/-/CHANGELOG.md
Classifier: Programming Language :: Python :: 3
Classifier: License :: OSI Approved :: MIT License
Classifier: Topic :: Software Development :: Disassemblers
Classifier: Topic :: Software Development :: Libraries
Classifier: Topic :: Software Development :: Libraries :: Python Modules
Classifier: Typing :: Typed
Requires-Python: >=3.9
License-File: LICENSE
Requires-Dist: rabbitizer<2.0.0,>=1.14.0
Dynamic: license-file
